<?xml version='1.0'?>
<order>
<color>E7E7F5</color>
<showterm>true</showterm>
<showdef>false</showdef>
<customDeckText>Custom Deck</customDeckText>
<wholeDeckText>Whole Deck</wholeDeckText>
<showText>SHOW</showText>
<addToText>Add to Custom</addToText>
<showTermText>Show Term</showTermText>
<showDefText>Show Definition</showDefText>
<orderset value='1'>
 <term>dimension</term>
 <def>An axis of an array.</def>
 <image></image>
 <width></width>
 <height></height>
</orderset>
<orderset value='2'>
 <term>list</term>
 <def>A single dimension array.</def>
 <image></image>
 <width></width>
 <height></height>
</orderset>
<orderset value='3'>
 <term>table</term>
 <def>A two dimension array.</def>
 <image></image>
 <width></width>
 <height></height>
</orderset>
<orderset value='4'>
 <term>array member</term>
 <def>An element or value in an array.</def>
 <image></image>
 <width></width>
 <height></height>
</orderset>
<orderset value='5'>
 <term>index</term>
 <def>An operator that allows us to reference a member of an array.</def>
 <image></image>
 <width></width>
 <height></height>
</orderset>
<orderset value='6'>
 <term>offset</term>
 <def>The method of referencing array members by starting at zero.</def>
 <image></image>
 <width></width>
 <height></height>
</orderset>
<orderset value='7'>
 <term>conditional compilation</term>
 <def>A compiler directive that includes or excludes lines of code based on a Boolean expression.</def>
 <image></image>
 <width></width>
 <height></height>
</orderset>
</order>
